cookie_consent/__init__.py
cookie_consent/admin.py
cookie_consent/apps.py
cookie_consent/cache.py
cookie_consent/conf.py
cookie_consent/forms.py
cookie_consent/managers.py
cookie_consent/middleware.py
cookie_consent/models.py
cookie_consent/urls.py
cookie_consent/util.py
cookie_consent/views.py
cookie_consent/fixtures/common_cookies.json
cookie_consent/migrations/0001_initial.py
cookie_consent/migrations/0002_auto__add_logitem.py
cookie_consent/migrations/__init__.py
cookie_consent/static/cookie_consent/cookiebar.js
cookie_consent/templates/cookie_consent/_cookie_group.html
cookie_consent/templates/cookie_consent/base.html
cookie_consent/templates/cookie_consent/cookiegroup_list.html
cookie_consent/templatetags/__init__.py
cookie_consent/templatetags/cookie_consent_tags.py
django_cookie_consent_pax-0.2.6.dist-info/AUTHORS
django_cookie_consent_pax-0.2.6.dist-info/LICENSE
django_cookie_consent_pax-0.2.6.dist-info/METADATA
django_cookie_consent_pax-0.2.6.dist-info/WHEEL
django_cookie_consent_pax-0.2.6.dist-info/top_level.txt
django_cookie_consent_pax-0.2.6.dist-info/RECORD
